{
   "database": {
     "driver": "mysqli",
     "host": "46.32.240.33",
     "user": "a-joo-za9-u-106563",
     "password": "DiGiuk#18",
     "name": "a-joo-za9-u-106563",
     "prefix": "kzr1_"
   },
   "theme": {
     "default": "awesome"
   },
   "system": {
     "list_limit": "20",
     "gzip": "0",
     "offset": "UTC",
     "display_errors":"true"
   },
   "google": {
   	 "client_secret":"Ni_tdSNE6de3oe8UKht7rm6c",
   	 "client_id":"821423007087-g9lbsn375ctt62eg30nt6kj4asjv5pi0.apps.googleusercontent.com"
   },
   
   "languages": [
     "en-GB"
   ]
 }